asserts/__init__.py
asserts/__init__.pyi
asserts/py.typed
asserts-0.14.0.dist-info/METADATA
asserts-0.14.0.dist-info/WHEEL
asserts-0.14.0.dist-info/licenses/LICENSE
asserts-0.14.0.dist-info/RECORD
