Metadata-Version: 2.4
Name: asserts
Version: 0.14.0
Summary: Stand-alone Assertions
License-Expression: MIT
License-File: LICENSE
Author: Sebastian Rittau
Author-email: sebastian.rittau@zfutura.de
Requires-Python: >= 3.10
Classifier: Development Status :: 3 - Alpha
Classifier: Intended Audience :: Developers
Classifier: Topic :: Software Development :: Quality Assurance
Classifier: Topic :: Software Development :: Testing
Requires-Dist: typing-extensions (>=4.10.0,<5)
Project-URL: Bug Tracker, https://github.com/srittau/python-asserts/issues
Project-URL: Changes, https://github.com/srittau/python-asserts/blob/main/CHANGELOG.md
Project-URL: GitHub, https://github.com/srittau/python-asserts
Project-URL: Homepage, https://github.com/srittau/python-asserts
Project-URL: Repository, https://github.com/srittau/python-asserts
